{
   "symbol_table": [
      {
         "variables": {
            "a": {
               "type": "int",
               "line": 3
            },
            "s": {
               "type": "string",
               "line": 4
            }
         },
         "functions": {},
         "types": {},
         "type": "script"
      }
   ],
   "ast": {
      "type": "script",
      "statements": [
         {
            "type": "define",
            "elements": [
               {
                  "id": "a",
                  "type": "int",
                  "line": 3,
                  "symbol": 0
               }
            ],
            "line": 3,
            "symbol": 0
         },
         {
            "type": "define",
            "elements": [
               {
                  "id": "s",
                  "type": "string",
                  "line": 4,
                  "symbol": 0
               }
            ],
            "line": 4,
            "symbol": 0
         },
         {
            "type": "expression",
            "op": "=",
            "left": {
               "type": "id",
               "value": "a",
               "line": 6,
               "symbol": 0,
               "t": "int"
            },
            "right": {
               "type": "id",
               "value": "s",
               "line": 6,
               "symbol": 0,
               "t": "string"
            },
            "line": 6,
            "symbol": 0,
            "t": ""
         }
      ],
      "line": 7,
      "symbol": 0
   },
   "error_list": [
      {
         "type": "TYPE_EXPRESSION",
         "line": 6,
         "elements": {
            "left": "int",
            "right": "string",
            "op": "="
         },
         "text": "Type expression error int = string"
      }
   ]
}